{
    "os": "macOS-14.6-arm64-arm-64bit",
    "python": "3.9.6",
    "heartbeatAt": "2024-08-16T03:16:35.625353",
    "startedAt": "2024-08-16T03:16:33.325440",
    "docker": null,
    "cuda": null,
    "args": [
        "--node-ip-address=127.0.0.1",
        "--node-manager-port=59494",
        "--object-store-name=/tmp/ray/session_2024-08-16_08-46-13_318583_25549/sockets/plasma_store",
        "--raylet-name=/tmp/ray/session_2024-08-16_08-46-13_318583_25549/sockets/raylet",
        "--redis-address=None",
        "--metrics-agent-port=64976",
        "--runtime-env-agent-port=63412",
        "--logging-rotate-bytes=536870912",
        "--logging-rotate-backup-count=5",
        "--runtime-env-agent-port=63412",
        "--gcs-address=127.0.0.1:64770",
        "--session-name=session_2024-08-16_08-46-13_318583_25549",
        "--temp-dir=/tmp/ray",
        "--webui=",
        "--cluster-id=704f48c0d3203fbbdfd5cf87768cce6a69d885d7a8413969e8690207",
        "--startup-token=21",
        "--worker-launch-time-ms=1723778186645",
        "--node-id=b3f1626e7494b3004a8e0ff571d0dbce53a7a9a4cbb3f00a4cf56823",
        "--runtime-env-hash=1"
    ],
    "state": "running",
    "program": "/Users/joykhera/Library/Caches/pypoetry/virtualenvs/evolution-E7IEFu2R-py3.9/lib/python3.9/site-packages/ray/_private/workers/default_worker.py",
    "codePathLocal": null,
    "host": "Joys-MacBook-Pro.local",
    "username": "joykhera",
    "executable": "/Users/joykhera/Library/Caches/pypoetry/virtualenvs/evolution-E7IEFu2R-py3.9/bin/python3",
    "cpu_count": 10,
    "cpu_count_logical": 10,
    "cpu_freq": {
        "current": 3228,
        "min": 600,
        "max": 3228
    },
    "cpu_freq_per_core": [
        {
            "current": 3228,
            "min": 600,
            "max": 3228
        }
    ],
    "disk": {
        "/": {
            "total": 460.4317207336426,
            "used": 10.09354019165039
        }
    },
    "gpuapple": {
        "type": "Apple M1 Pro",
        "vendor": "sppci_vendor_Apple"
    },
    "memory": {
        "total": 16.0
    }
}
